colorlogs/__init__.py
colorlogs/colorlogs.py
colorlogs-0.1.dist-info/METADATA
colorlogs-0.1.dist-info/WHEEL
colorlogs-0.1.dist-info/top_level.txt
colorlogs-0.1.dist-info/RECORD
