Metadata-Version: 1.0
Name: colorlogs
Version: 0.1
Summary: Custom logger allows colored logs
Home-page: https://github.com/karthiktv90/python_utilities
Author: karthik
Author-email: karthik@mymail.com
License: UNH
Platform: UNKNOWN
